tchess/__init__.py
tchess/__main__.py
tchess/moves.py
tchess/server.py
tchess/tchess.py
tchess-0.0.32.data/data/man/man1/tchess.1
tchess-0.0.32.data/scripts/tchess
tchess-0.0.32.dist-info/LICENSE
tchess-0.0.32.dist-info/METADATA
tchess-0.0.32.dist-info/WHEEL
tchess-0.0.32.dist-info/top_level.txt
tchess-0.0.32.dist-info/RECORD
