Metadata-Version: 2.1
Name: tchess
Version: 0.0.32
Summary: The Chess game in terminal
Home-page: https://github.com/parsampsh/tchess
Author: parsa shahmaleki
Author-email: parsampsh@gmail.com
License: UNKNOWN
Platform: UNKNOWN
Classifier: Programming Language :: Python :: 3
Classifier: Operating System :: OS Independent
Classifier: License :: OSI Approved :: MIT License
Requires-Python: >=3.6
Requires-Dist: Flask (>=1.1)
Requires-Dist: requests (>=2.0)
Requires-Dist: karafs (>=0.1.1)
